webpub_manifest_parser/__init__.py
webpub_manifest_parser/core/__init__.py
webpub_manifest_parser/core/ast.py
webpub_manifest_parser/core/errors.py
webpub_manifest_parser/core/parsers.py
webpub_manifest_parser/core/properties.py
webpub_manifest_parser/core/registry.py
webpub_manifest_parser/core/semantic.py
webpub_manifest_parser/core/syntax.py
webpub_manifest_parser/epub/__init__.py
webpub_manifest_parser/epub/ast.py
webpub_manifest_parser/errors.py
webpub_manifest_parser/opds2/__init__.py
webpub_manifest_parser/opds2/ast.py
webpub_manifest_parser/opds2/parsers.py
webpub_manifest_parser/opds2/registry.py
webpub_manifest_parser/opds2/semantic.py
webpub_manifest_parser/opds2/syntax.py
webpub_manifest_parser/rwpm/__init__.py
webpub_manifest_parser/rwpm/ast.py
webpub_manifest_parser/rwpm/parser.py
webpub_manifest_parser/rwpm/registry.py
webpub_manifest_parser/rwpm/semantic.py
webpub_manifest_parser/rwpm/syntax.py
webpub_manifest_parser/utils.py
webpub_manifest_parser-0.0.4.dist-info/LICENSE
webpub_manifest_parser-0.0.4.dist-info/WHEEL
webpub_manifest_parser-0.0.4.dist-info/METADATA
webpub_manifest_parser-0.0.4.dist-info/RECORD
