Metadata-Version: 2.1
Name: webpub-manifest-parser
Version: 0.0.4
Summary: A parser for the Readium Web Publication Manifest and OPDS 2.0 formats.
Home-page: https://github.com/NYPL-Simplified/python-webpub-manifest-parser
License: Apache-2.0
Keywords: Readium Web Publication Manifest,RWPM,Open Publication Distribution System 2.0,OPDS 2.0
Author: Leonard Richardson
Author-email: leonardr@segfault.org
Maintainer: Viacheslav Bessonov
Maintainer-email: viacheslav.bessonov@hilbertteam.com
Requires-Python: >=2.7, !=3.0.*, !=3.1.*, !=3.2.*, !=3.3.*, !=3.4.*
Classifier: Intended Audience :: Developers
Classifier: License :: OSI Approved :: Apache Software License
Classifier: Operating System :: OS Independent
Classifier: Programming Language :: Python
Classifier: Programming Language :: Python :: 2
Classifier: Programming Language :: Python :: 2.7
Classifier: Programming Language :: Python :: 3
Classifier: Programming Language :: Python :: 3.5
Classifier: Programming Language :: Python :: 3.6
Classifier: Programming Language :: Python :: 3.7
Classifier: Programming Language :: Python :: 3.8
Classifier: Programming Language :: Python :: Implementation :: CPython
Classifier: Topic :: Software Development :: Libraries :: Python Modules
Requires-Dist: enum34 (>=1.1.10,<2.0.0)
Requires-Dist: jsonschema (>=3.2.0,<4.0.0)
Requires-Dist: multipledispatch (>=0.6.0,<0.7.0)
Requires-Dist: pyrsistent (==0.16.1)
Requires-Dist: rfc3987 (>=1.3.8,<2.0.0)
Requires-Dist: strict-rfc3339 (>=0.7,<0.8)
Requires-Dist: uritemplate (>=3.0.1,<4.0.0)
Project-URL: Repository, https://github.com/NYPL-Simplified/python-webpub-manifest-parser
